[
  {
    "id": "prophets-hadiths-01",
    "packId": "prophets-hadiths",
    "category": "all",
    "title": "Intentions",
    "questionType": "multiple-choice",
    "promptText": "Complete the hadith: 'Actions are judged by ___.’",
    "answerText": "Intentions.",
    "options": ["Intentions", "Wealth", "Travel", "Victory"],
    "correctIndex": 0,
    "sourceTitle": "Sahih al-Bukhari 1",
    "explanation": "This hadith is a foundation for sincerity in every deed.",
    "difficulty": "easy"
  },
  {
    "id": "prophets-hadiths-02",
    "packId": "prophets-hadiths",
    "category": "all",
    "title": "First Revelation",
    "questionType": "multiple-choice",
    "promptText": "In which cave did the Prophet Muhammad receive the first revelation?",
    "answerText": "Cave Hira.",
    "options": ["Cave Hira", "Cave Thawr", "Mount Sinai", "Arafah"],
    "correctIndex": 0,
    "sourceTitle": "Seerah",
    "explanation": "The first words revealed there were 'Iqra'.",
    "difficulty": "easy"
  },
  {
    "id": "prophets-hadiths-03",
    "packId": "prophets-hadiths",
    "category": "all",
    "title": "Best to Family",
    "questionType": "fill-blank",
    "promptText": "Complete the hadith: 'The best of you are those who are best to their ___.’",
    "answerText": "Families.",
    "options": ["neighbors", "families", "teachers", "leaders"],
    "correctIndex": 1,
    "sourceTitle": "At-Tirmidhi",
    "explanation": "Good character begins at home.",
    "difficulty": "easy"
  },
  {
    "id": "prophets-hadiths-04",
    "packId": "prophets-hadiths",
    "category": "all",
    "title": "Prophet Yunus",
    "questionType": "multiple-choice",
    "promptText": "Which Prophet was swallowed by a whale?",
    "answerText": "Prophet Yunus.",
    "options": ["Prophet Yunus", "Prophet Musa", "Prophet Dawud", "Prophet Yusuf"],
    "correctIndex": 0,
    "sourceTitle": "Quran 21:87",
    "explanation": "His story teaches repentance and hope in Allah's mercy.",
    "difficulty": "easy"
  },
  {
    "id": "prophets-hadiths-05",
    "packId": "prophets-hadiths",
    "category": "all",
    "title": "Hadith Collections",
    "questionType": "match",
    "promptText": "Match the hadith collection idea to its title.",
    "answerText": "Correct hadith collection matching.",
    "matchPairs": [
      { "left": "Al-Sahihayn", "right": "Bukhari and Muslim" },
      { "left": "Kutub as-Sittah", "right": "Six major hadith collections" },
      { "left": "Hadith of Jibril", "right": "Islam, Iman, Ihsan" }
    ],
    "sourceTitle": "Hadith studies",
    "explanation": "These are core orientation points for hadith learning.",
    "difficulty": "medium"
  },
  {
    "id": "prophets-hadiths-06",
    "packId": "prophets-hadiths",
    "category": "all",
    "title": "Ulul Azm",
    "questionType": "multiple-choice",
    "promptText": "What is the title for the messengers of greatest resolve?",
    "answerText": "Ulul 'Azm.",
    "options": ["Ulul 'Azm", "Ansar", "Muhajirun", "Muttaqun"],
    "correctIndex": 0,
    "sourceTitle": "Quran 46:35",
    "explanation": "This title honors a distinguished group of messengers.",
    "difficulty": "medium"
  },
  {
    "id": "prophets-hadiths-07",
    "packId": "prophets-hadiths",
    "category": "all",
    "title": "Prophetic Order",
    "questionType": "sequence",
    "promptText": "Tap these events of the Prophet's life in the correct order.",
    "answerText": "First revelation, Hijrah, Badr, Farewell Hajj.",
    "sequenceSteps": ["First revelation", "Hijrah to Madinah", "Battle of Badr", "Farewell Hajj"],
    "sourceTitle": "Seerah timeline",
    "explanation": "A simple timeline helps learners place major events properly.",
    "difficulty": "hard"
  },
  {
    "id": "prophets-hadiths-08",
    "packId": "prophets-hadiths",
    "category": "all",
    "title": "Cleanliness",
    "questionType": "multiple-choice",
    "promptText": "Complete the hadith: 'Cleanliness is ___ of faith.’",
    "answerText": "Half.",
    "options": ["Part", "Half", "Proof", "Light"],
    "correctIndex": 1,
    "sourceTitle": "Sahih Muslim 223",
    "explanation": "Purity and worship are tightly connected in Islam.",
    "difficulty": "easy"
  },
  {
    "id": "prophets-hadiths-09",
    "packId": "prophets-hadiths",
    "category": "all",
    "title": "Treaty of Hudaybiyyah",
    "questionType": "multiple-choice",
    "promptText": "What major agreement was called a 'clear victory' in the Quran?",
    "answerText": "The Treaty of Hudaybiyyah.",
    "options": ["The Treaty of Hudaybiyyah", "The Constitution of Madinah", "The Pledge of Aqabah", "The Farewell Sermon"],
    "correctIndex": 0,
    "sourceTitle": "Quran 48:1",
    "explanation": "What looked difficult became a turning point for growth.",
    "difficulty": "medium"
  },
  {
    "id": "prophets-hadiths-10",
    "packId": "prophets-hadiths",
    "category": "all",
    "title": "Speech Ethics",
    "questionType": "fill-blank",
    "promptText": "Complete the hadith: 'Let him speak good or ___.’",
    "answerText": "Remain silent.",
    "options": ["sit down", "remain silent", "make wudu", "smile"],
    "correctIndex": 1,
    "sourceTitle": "Sahih al-Bukhari / Sahih Muslim",
    "explanation": "The hadith teaches discipline of speech and character.",
    "difficulty": "easy"
  }
]
